LICENSE
README.md
setup.py
burmesedate/__init__.py
burmesedate/astro.py
burmesedate/burme.py
burmesedate/burmesedate.py
burmesedate/genju.py
burmesedate/helpers.py
burmesedate/lists.py
burmesedate/translate.py
burmesedate.egg-info/PKG-INFO
burmesedate.egg-info/SOURCES.txt
burmesedate.egg-info/dependency_links.txt
burmesedate.egg-info/requires.txt
burmesedate.egg-info/top_level.txt
test/test_astro.py
test/test_bur.py
test/test_cy.py
test/test_genju.py
test/test_gmc.py
test/test_j2b.py