Metadata-Version: 2.1
Name: burmesedate
Version: 0.0.1
Summary: Burmese Calendar API in Python
Home-page: https://github.com/phothinmg/burmesedate-py/blob/main/README.md
Author: Pho Thin Maung
Author-email: phothinmg@gmail.com
License: MIT
Project-URL: Source Code, https://github.com/phothinmg/burmesedate-py/tree/main/burmesedate
Project-URL: Bug Tracker, https://github.com/phothinmg/burmesedate-py/issues
Project-URL: Documentation, https://phothinmg.github.io/burmesedate-py/burmesedate.html
License-File: LICENSE
Requires-Dist: requests
Provides-Extra: dev
Requires-Dist: pytest; extra == "dev"
Requires-Dist: pylint; extra == "dev"
Requires-Dist: coverage; extra == "dev"
Requires-Dist: black; extra == "dev"
Requires-Dist: genbadge; extra == "dev"
